rfc7578
