Metadata-Version: 2.1
Name: rfc7578
Version: 1.0.1
Summary: Python implementation of RFC7578 (multipart/form-data)
Home-page: https://pypi.org/project/rfc7578
Author: Adam Jenca
Author-email: jenca.adam@gmail.com
License: UNKNOWN
Platform: UNKNOWN
